git_notion_pretty/__init__.py
git_notion_pretty/cli.py
git_notion_pretty/git_notion.py
git_notion_pretty-1.0.4.dist-info/LICENSE
git_notion_pretty-1.0.4.dist-info/METADATA
git_notion_pretty-1.0.4.dist-info/WHEEL
git_notion_pretty-1.0.4.dist-info/entry_points.txt
git_notion_pretty-1.0.4.dist-info/top_level.txt
git_notion_pretty-1.0.4.dist-info/RECORD
