Metadata-Version: 2.1
Name: git-notion-pretty
Version: 1.0.4
Summary: Syncs GitHub Markdown files to Notion
Home-page: https://github.com/Harbor-Systems/git-notion
Author: NarekA
License: MIT license
Keywords: git_notion_pretty
Classifier: Development Status :: 2 - Pre-Alpha
Classifier: Intended Audience :: Developers
Classifier: License :: OSI Approved :: MIT License
Classifier: Natural Language :: English
Classifier: Programming Language :: Python :: 3
Classifier: Programming Language :: Python :: 3.5
Classifier: Programming Language :: Python :: 3.6
Classifier: Programming Language :: Python :: 3.7
Classifier: Programming Language :: Python :: 3.8
Requires-Python: >=3.5
License-File: LICENSE
Requires-Dist: docopt
Requires-Dist: md2notion
